collidoscope/__init__.py
collidoscope/__main__.py
collidoscope/babelfont.py
collidoscope-0.6.5.dist-info/AUTHORS.txt
collidoscope-0.6.5.dist-info/LICENSE
collidoscope-0.6.5.dist-info/METADATA
collidoscope-0.6.5.dist-info/WHEEL
collidoscope-0.6.5.dist-info/top_level.txt
collidoscope-0.6.5.dist-info/RECORD
