Metadata-Version: 2.1
Name: collidoscope
Version: 0.6.5
Summary: Brute force detection of glyph collisions
Home-page: https://github.com/simoncozens/collidoscope
Author: Simon Cozens
Author-email: simon@simon-cozens.org
License: MIT
Classifier: Programming Language :: Python
Classifier: Programming Language :: Python :: 2
Classifier: Programming Language :: Python :: 3
Classifier: License :: OSI Approved :: MIT License
Classifier: Development Status :: 4 - Beta
License-File: LICENSE
License-File: AUTHORS.txt
